fleetmqsdk/Abc_config_pb2.py
fleetmqsdk/Message_pb2.py
fleetmqsdk/__init__.py
fleetmqsdk/fleetmqsdk.py
fleetmqsdk/logger.py
fleetmqsdk/utils.py
fleetmqsdk-0.0.19.dist-info/METADATA
fleetmqsdk-0.0.19.dist-info/WHEEL
fleetmqsdk-0.0.19.dist-info/top_level.txt
fleetmqsdk-0.0.19.dist-info/RECORD
