Metadata-Version: 2.4
Name: fleetmqsdk
Version: 0.0.19
Summary: A convenient SDK for FleetMQ
Author: Nicole
Author-email: nicole@fleetmq.io
Classifier: Programming Language :: Python :: 3
Classifier: License :: OSI Approved :: MIT License
Requires-Dist: google-api-python-client
Requires-Dist: pyzmq
Requires-Dist: setuptools
Dynamic: author
Dynamic: author-email
Dynamic: classifier
Dynamic: requires-dist
Dynamic: summary
